brickrepl/__init__.py
brickrepl/hub.py
brickrepl/motor.py
brickrepl/repl.py
brickrepl/rfcomm.py
brickrepl-0.1.1.dist-info/METADATA
brickrepl-0.1.1.dist-info/WHEEL
brickrepl-0.1.1.dist-info/top_level.txt
brickrepl-0.1.1.dist-info/RECORD
