Metadata-Version: 2.4
Name: brickrepl
Version: 0.1.1
Summary: Control LEGO Robot Inventor 51515 hubs from EV3 via RFCOMM using MAC address
Author: ollie
Requires-Python: >=3.5
Dynamic: author
Dynamic: requires-python
Dynamic: summary
